MANIFEST.in
README.md
setup.py
version.py
src/toil_rnaseq/__init__.py
src/toil_rnaseq/input_generation.py
src/toil_rnaseq/toil_rnaseq.py
src/toil_rnaseq.egg-info/PKG-INFO
src/toil_rnaseq.egg-info/SOURCES.txt
src/toil_rnaseq.egg-info/dependency_links.txt
src/toil_rnaseq.egg-info/entry_points.txt
src/toil_rnaseq.egg-info/requires.txt
src/toil_rnaseq.egg-info/top_level.txt
src/toil_rnaseq/test/__init__.py
src/toil_rnaseq/test/test_rnaseq_cgl.py
src/toil_rnaseq/tools/__init__.py
src/toil_rnaseq/tools/aligners.py
src/toil_rnaseq/tools/bams.py
src/toil_rnaseq/tools/jobs.py
src/toil_rnaseq/tools/preprocessing.py
src/toil_rnaseq/tools/qc.py
src/toil_rnaseq/tools/quantifiers.py
src/toil_rnaseq/utils/__init__.py
src/toil_rnaseq/utils/expando.py
src/toil_rnaseq/utils/files.py
src/toil_rnaseq/utils/filesize.py
src/toil_rnaseq/utils/urls.py