Metadata-Version: 1.0
Name: toil-rnaseq
Version: 4.1.2
Summary: UC Santa Cruz Computational Genomics Lab's Toil-based RNA-seq workflow
Home-page: https://github.com/BD2KGenomics/toil-lib
Author: UCSC Computational Genomics Lab
Author-email: cgl-toil@googlegroups.com
License: UNKNOWN
Platform: UNKNOWN
